[  {    "type": "post",    "url": "/auth",    "title": "Authenticate",    "name": "Authenticate",    "group": "Authentication",    "parameter": {      "fields": {        "Parameter": [          {            "group": "Parameter",            "type": "String",            "optional": false,            "field": "email",            "description": "<p>Organization's email</p>"          },          {            "group": "Parameter",            "type": "String",            "optional": false,            "field": "password",            "description": "<p>Organization's password</p>"          }        ]      }    },    "success": {      "fields": {        "200": [          {            "group": "200",            "type": "Number",            "optional": false,            "field": "id",            "description": "<p>ID of organization</p>"          },          {            "group": "200",            "type": "String",            "optional": false,            "field": "token",            "description": "<p>Authorization token for use in requests</p>"          },          {            "group": "200",            "type": "String",            "optional": false,            "field": "message",            "description": "<p>Descriptive message</p>"          }        ]      }    },    "version": "0.0.0",    "filename": "controllers/auth.js",    "groupTitle": "Authentication"  },  {    "type": "post",    "url": "/auth/register",    "title": "Register an organization",    "name": "Register",    "group": "Authentication",    "parameter": {      "fields": {        "Parameter": [          {            "group": "Parameter",            "type": "String",            "optional": false,            "field": "email",            "description": "<p>Organization's email</p>"          },          {            "group": "Parameter",            "type": "String",            "optional": false,            "field": "password",            "description": "<p>Organization's password</p>"          },          {            "group": "Parameter",            "type": "String",            "optional": false,            "field": "name",            "description": "<p>Organization's name</p>"          }        ]      }    },    "success": {      "fields": {        "201": [          {            "group": "201",            "type": "Number",            "optional": false,            "field": "id",            "description": "<p>ID of organization</p>"          },          {            "group": "201",            "type": "String",            "optional": false,            "field": "message",            "description": "<p>Descriptive message</p>"          }        ]      }    },    "version": "0.0.0",    "filename": "controllers/auth.js",    "groupTitle": "Authentication"  },  {    "type": "head",    "url": "/auth/verify",    "title": "Verify authentication",    "name": "Verify",    "group": "Authentication",    "parameter": {      "fields": {        "Parameter": [          {            "group": "Parameter",            "type": "String",            "optional": false,            "field": "email",            "description": "<p>User's email</p>"          },          {            "group": "Parameter",            "type": "String",            "optional": false,            "field": "password",            "description": "<p>User's password</p>"          }        ]      }    },    "success": {      "fields": {        "200": [          {            "group": "200",            "optional": false,            "field": "empty",            "description": "<p>No response body</p>"          }        ]      }    },    "version": "0.0.0",    "filename": "controllers/auth.js",    "groupTitle": "Authentication"  },  {    "type": "put",    "url": "/brand",    "title": "Create a brand",    "name": "CreateBrand",    "group": "Brand",    "parameter": {      "fields": {        "Parameter": [          {            "group": "Parameter",            "type": "String",            "size": "0...255",            "optional": false,            "field": "name",            "description": "<p>Name of brand</p>"          }        ]      }    },    "success": {      "fields": {        "200": [          {            "group": "200",            "type": "String",            "optional": false,            "field": "message",            "description": "<p>Descriptive message</p>"          },          {            "group": "200",            "type": "Number",            "optional": false,            "field": "id",            "description": "<p>ID of created row</p>"          }        ]      }    },    "version": "0.0.0",    "filename": "controllers/brand.js",    "groupTitle": "Brand"  },  {    "type": "delete",    "url": "/brand/:brandID",    "title": "Delete a brand",    "name": "DeleteBrand",    "group": "Brand",    "success": {      "fields": {        "200": [          {            "group": "200",            "type": "String",            "optional": false,            "field": "message",            "description": "<p>Descriptive message</p>"          }        ],        "204": [          {            "group": "204",            "optional": false,            "field": "empty",            "description": "<p>No body when item was already deleted</p>"          }        ]      }    },    "version": "0.0.0",    "filename": "controllers/brand.js",    "groupTitle": "Brand"  },  {    "type": "get",    "url": "/brand/:brandID",    "title": "Get brand",    "name": "GetBrand",    "group": "Brand",    "version": "0.0.0",    "filename": "controllers/brand.js",    "groupTitle": "Brand",    "examples": [      {        "title": "Response format:",        "content": "{\n  \"brandID\": 0,\n  \"organizationID\": 0,\n  \"name\": \"\"\n}",        "type": "json"      }    ]  },  {    "type": "get",    "url": "/brand",    "title": "Get all brands",    "name": "GetBrands",    "group": "Brand",    "examples": [      {        "title": "Response format:",        "content": "{\n  results: [\n    {\n      \"brandID\": 0,\n      \"organizationID\": 0,\n      \"name\": \"\"\n    }\n  ]\n}",        "type": "json"      }    ],    "version": "0.0.0",    "filename": "controllers/brand.js",    "groupTitle": "Brand"  },  {    "type": "put",    "url": "/brand/:brandID",    "title": "Update a brand",    "name": "UpdateBrand",    "group": "Brand",    "parameter": {      "fields": {        "Parameter": [          {            "group": "Parameter",            "type": "String",            "size": "0...255",            "optional": true,            "field": "name",            "description": "<p>Name of brand</p>"          }        ]      }    },    "version": "0.0.0",    "filename": "controllers/brand.js",    "groupTitle": "Brand",    "examples": [      {        "title": "Response format:",        "content": "{\n  \"brandID\": 0,\n  \"organizationID\": 0,\n  \"name\": \"\"\n}",        "type": "json"      }    ]  },  {    "type": "put",    "url": "/category",    "title": "Create a category",    "name": "CreateCategory",    "group": "Category",    "parameter": {      "fields": {        "Parameter": [          {            "group": "Parameter",            "type": "String",            "size": "0...255",            "optional": false,            "field": "name",            "description": "<p>Name of category</p>"          }        ]      }    },    "success": {      "fields": {        "200": [          {            "group": "200",            "type": "String",            "optional": false,            "field": "message",            "description": "<p>Descriptive message</p>"          },          {            "group": "200",            "type": "Number",            "optional": false,            "field": "id",            "description": "<p>ID of created row</p>"          }        ]      }    },    "version": "0.0.0",    "filename": "controllers/category.js",    "groupTitle": "Category"  },  {    "type": "delete",    "url": "/category/:categoryID",    "title": "Delete a category",    "name": "DeleteCategory",    "group": "Category",    "success": {      "fields": {        "200": [          {            "group": "200",            "type": "String",            "optional": false,            "field": "message",            "description": "<p>Descriptive message</p>"          }        ],        "204": [          {            "group": "204",            "optional": false,            "field": "empty",            "description": "<p>No body when item was already deleted</p>"          }        ]      }    },    "version": "0.0.0",    "filename": "controllers/category.js",    "groupTitle": "Category"  },  {    "type": "get",    "url": "/category",    "title": "Get all categories",    "name": "GetCategories",    "group": "Category",    "examples": [      {        "title": "Response format:",        "content": "{\n  results: [\n    {\n      \"categoryID\": 0,\n      \"organizationID\": 0,\n      \"name\": \"\"\n    }\n  ]\n}",        "type": "json"      }    ],    "version": "0.0.0",    "filename": "controllers/category.js",    "groupTitle": "Category"  },  {    "type": "get",    "url": "/category/:categoryID",    "title": "Get category",    "name": "GetCategory",    "group": "Category",    "version": "0.0.0",    "filename": "controllers/category.js",    "groupTitle": "Category",    "examples": [      {        "title": "Response format:",        "content": "{\n  \"categoryID\": 0,\n  \"organizationID\": 0,\n  \"name\": \"\"\n}",        "type": "json"      }    ]  },  {    "type": "put",    "url": "/category/:categoryID",    "title": "Update a category",    "name": "UpdateCategory",    "group": "Category",    "parameter": {      "fields": {        "Parameter": [          {            "group": "Parameter",            "type": "String",            "size": "0...255",            "optional": true,            "field": "name",            "description": "<p>Name of category</p>"          }        ]      }    },    "version": "0.0.0",    "filename": "controllers/category.js",    "groupTitle": "Category",    "examples": [      {        "title": "Response format:",        "content": "{\n  \"categoryID\": 0,\n  \"organizationID\": 0,\n  \"name\": \"\"\n}",        "type": "json"      }    ]  },  {    "type": "put",    "url": "/item",    "title": "Create an item",    "name": "CreateItem",    "group": "Item",    "parameter": {      "fields": {        "Parameter": [          {            "group": "Parameter",            "type": "Number",            "optional": true,            "field": "modelID",            "description": "<p>ID of model</p>"          },          {            "group": "Parameter",            "type": "Number",            "optional": true,            "field": "categoryID",            "description": "<p>ID of category</p>"          },          {            "group": "Parameter",            "type": "String",            "optional": false,            "field": "tag",            "description": "<p>Unique identifier of item</p>"          }        ]      }    },    "success": {      "fields": {        "200": [          {            "group": "200",            "type": "String",            "optional": false,            "field": "message",            "description": "<p>Descriptive message</p>"          },          {            "group": "200",            "type": "Number",            "optional": false,            "field": "id",            "description": "<p>ID of created row</p>"          }        ]      }    },    "version": "0.0.0",    "filename": "controllers/item.js",    "groupTitle": "Item"  },  {    "type": "delete",    "url": "/item/:tag",    "title": "Delete item",    "name": "DeleteItem",    "group": "Item",    "success": {      "fields": {        "200": [          {            "group": "200",            "type": "String",            "optional": false,            "field": "message",            "description": "<p>Descriptive message</p>"          }        ],        "204": [          {            "group": "204",            "optional": false,            "field": "empty",            "description": "<p>No body when item was already deleted</p>"          }        ]      }    },    "version": "0.0.0",    "filename": "controllers/item.js",    "groupTitle": "Item"  },  {    "type": "get",    "url": "/item/:tag",    "title": "Get an item",    "name": "GetItem",    "group": "Item",    "version": "0.0.0",    "filename": "controllers/item.js",    "groupTitle": "Item",    "examples": [      {        "title": "Response format:",        "content": "{\n  \"itemID\": 0,\n  \"organizationID\": 0,\n  \"modelID\": 0,\n  \"categoryID\": 0,\n  \"tag\": \"234234\"\n}",        "type": "json"      }    ]  },  {    "type": "get",    "url": "/item",    "title": "Get all items",    "name": "GetItems",    "group": "Item",    "parameter": {      "fields": {        "Parameter": [          {            "group": "Parameter",            "type": "Number",            "optional": true,            "field": "brandID",            "description": "<p>Return items with only this brandID</p>"          },          {            "group": "Parameter",            "type": "Number",            "optional": true,            "field": "modelID",            "description": "<p>Return items with only this modelID</p>"          },          {            "group": "Parameter",            "type": "Number",            "optional": true,            "field": "categoryID",            "description": "<p>Return items with only this categoryID</p>"          }        ]      }    },    "examples": [      {        "title": "Response format:",        "content": "{\n  results: [\n    {\n      \"itemID\": 0,\n      \"organizationID\": 0,\n      \"modelID\": 0,\n      \"categoryID\": 0,\n      \"tag\": \"234234\"\n    }\n  ]\n}",        "type": "json"      }    ],    "version": "0.0.0",    "filename": "controllers/item.js",    "groupTitle": "Item"  },  {    "type": "put",    "url": "/item/:tag",    "title": "Update item",    "name": "UpdateItem",    "group": "Item",    "parameter": {      "fields": {        "Parameter": [          {            "group": "Parameter",            "type": "Number",            "optional": true,            "field": "modelID",            "description": "<p>ID of model</p>"          },          {            "group": "Parameter",            "type": "Number",            "optional": true,            "field": "categoryID",            "description": "<p>ID of category</p>"          },          {            "group": "Parameter",            "type": "String",            "optional": true,            "field": "tag",            "description": "<p>Unique identifier of item</p>"          }        ]      }    },    "version": "0.0.0",    "filename": "controllers/item.js",    "groupTitle": "Item",    "examples": [      {        "title": "Response format:",        "content": "{\n  \"itemID\": 0,\n  \"organizationID\": 0,\n  \"modelID\": 0,\n  \"categoryID\": 0,\n  \"tag\": \"234234\"\n}",        "type": "json"      }    ]  },  {    "type": "get",    "url": "/",    "title": "Get main",    "name": "GetMain",    "group": "Main",    "description": "<p>This is the entry point for the API. Using HAL relations, the client can navigate the whole API based on the response from this endpoint.</p>",    "success": {      "fields": {        "200": [          {            "group": "200",            "optional": false,            "field": "empty",            "description": "<p>No response body</p>"          }        ]      }    },    "version": "0.0.0",    "filename": "controllers/main.js",    "groupTitle": "Main"  },  {    "type": "put",    "url": "/model",    "title": "Create a model",    "name": "CreateModel",    "group": "Model",    "parameter": {      "fields": {        "Parameter": [          {            "group": "Parameter",            "type": "String",            "size": "0...255",            "optional": false,            "field": "name",            "description": "<p>Name of model</p>"          },          {            "group": "Parameter",            "type": "Number",            "optional": false,            "field": "brandID",            "description": "<p>ID of a brand</p>"          }        ]      }    },    "success": {      "fields": {        "200": [          {            "group": "200",            "type": "String",            "optional": false,            "field": "message",            "description": "<p>Descriptive message</p>"          },          {            "group": "200",            "type": "Number",            "optional": false,            "field": "id",            "description": "<p>ID of created row</p>"          }        ]      }    },    "version": "0.0.0",    "filename": "controllers/model.js",    "groupTitle": "Model"  },  {    "type": "delete",    "url": "/model/:modelID",    "title": "Delete a model",    "name": "DeleteModel",    "group": "Model",    "success": {      "fields": {        "200": [          {            "group": "200",            "type": "String",            "optional": false,            "field": "message",            "description": "<p>Descriptive message</p>"          }        ],        "204": [          {            "group": "204",            "optional": false,            "field": "empty",            "description": "<p>No body when item was already deleted</p>"          }        ]      }    },    "version": "0.0.0",    "filename": "controllers/model.js",    "groupTitle": "Model"  },  {    "type": "get",    "url": "/model/:modelID",    "title": "Get model",    "name": "GetModel",    "group": "Model",    "version": "0.0.0",    "filename": "controllers/model.js",    "groupTitle": "Model",    "examples": [      {        "title": "Response format:",        "content": "{\n  \"modelID\": 0,\n  \"brandID\": 0,\n  \"organizationID\": 0,\n  \"name\": \"\"\n}",        "type": "json"      }    ]  },  {    "type": "get",    "url": "/model",    "title": "Get all models",    "name": "GetModels",    "group": "Model",    "examples": [      {        "title": "Response format:",        "content": "{\n  results: [\n    {\n      \"modelID\": 0,\n      \"brandID\": 0,\n      \"organizationID\": 0,\n      \"name\": \"\"\n    }\n  ]\n}",        "type": "json"      }    ],    "version": "0.0.0",    "filename": "controllers/model.js",    "groupTitle": "Model"  },  {    "type": "put",    "url": "/model/:modelID",    "title": "Update a model",    "name": "UpdateModel",    "group": "Model",    "parameter": {      "fields": {        "Parameter": [          {            "group": "Parameter",            "type": "String",            "size": "0...255",            "optional": true,            "field": "name",            "description": "<p>Name of model</p>"          },          {            "group": "Parameter",            "type": "Number",            "optional": true,            "field": "brandID",            "description": "<p>ID of a brand</p>"          }        ]      }    },    "version": "0.0.0",    "filename": "controllers/model.js",    "groupTitle": "Model",    "examples": [      {        "title": "Response format:",        "content": "{\n  \"modelID\": 0,\n  \"brandID\": 0,\n  \"organizationID\": 0,\n  \"name\": \"\"\n}",        "type": "json"      }    ]  },  {    "type": "put",    "url": "/organization",    "title": "Create an organization",    "name": "CreateOrganization",    "group": "Organization",    "description": "<p>Not implemented.</p>",    "success": {      "fields": {        "200": [          {            "group": "200",            "optional": false,            "field": "empty",            "description": "<p>No response body</p>"          }        ]      }    },    "version": "0.0.0",    "filename": "controllers/organization.js",    "groupTitle": "Organization"  },  {    "type": "get",    "url": "/organization/:organizationID",    "title": "Delete an organization",    "name": "DeleteOrganization",    "group": "Organization",    "description": "<p>Not implemented.</p>",    "success": {      "fields": {        "200": [          {            "group": "200",            "optional": false,            "field": "empty",            "description": "<p>No response body</p>"          }        ]      }    },    "version": "0.0.0",    "filename": "controllers/organization.js",    "groupTitle": "Organization"  },  {    "type": "get",    "url": "/organization/:organizationID",    "title": "Get an organization",    "name": "GetOrganization",    "group": "Organization",    "description": "<p>Not implemented.</p>",    "success": {      "fields": {        "200": [          {            "group": "200",            "optional": false,            "field": "empty",            "description": "<p>No response body</p>"          }        ]      }    },    "version": "0.0.0",    "filename": "controllers/organization.js",    "groupTitle": "Organization"  },  {    "type": "put",    "url": "/organization/:organizationID",    "title": "Update an organization",    "name": "UpdateOrganization",    "group": "Organization",    "description": "<p>Not implemented.</p>",    "success": {      "fields": {        "200": [          {            "group": "200",            "optional": false,            "field": "empty",            "description": "<p>No response body</p>"          }        ]      }    },    "version": "0.0.0",    "filename": "controllers/organization.js",    "groupTitle": "Organization"  },  {    "type": "put",    "url": "/rental",    "title": "Create arental",    "name": "CreateRental",    "group": "Rental",    "success": {      "fields": {        "200": [          {            "group": "200",            "type": "String",            "optional": false,            "field": "message",            "description": "<p>Descriptive message</p>"          },          {            "group": "200",            "type": "Number",            "optional": false,            "field": "id",            "description": "<p>ID of created row</p>"          }        ]      }    },    "version": "0.0.0",    "filename": "controllers/rental.js",    "groupTitle": "Rental"  },  {    "type": "delete",    "url": "/rental/:rentalID",    "title": "Delete a rental",    "name": "DeleteRental",    "group": "Rental",    "success": {      "fields": {        "200": [          {            "group": "200",            "type": "String",            "optional": false,            "field": "message",            "description": "<p>Descriptive message</p>"          }        ],        "204": [          {            "group": "204",            "optional": false,            "field": "empty",            "description": "<p>No body when item was already deleted</p>"          }        ]      }    },    "version": "0.0.0",    "filename": "controllers/rental.js",    "groupTitle": "Rental"  },  {    "type": "get",    "url": "/rental/:rentalID",    "title": "Get a rental",    "name": "GetRental",    "group": "Rental",    "version": "0.0.0",    "filename": "controllers/rental.js",    "groupTitle": "Rental",    "examples": [      {        "title": "Response format:",        "content": "{\n  \"endDate\": \"2017-02-23T05:00:00.000Z\",\n  \"itemID\": 0,\n  \"organizationID\": 0,\n  \"rentalID\": 0,\n  \"returnDate\": null,\n  \"startDate\": \"2017-02-22T05:00:00.000Z\",\n  \"tag\": \"\",\n  \"userID\": null\n}",        "type": "json"      }    ]  },  {    "type": "get",    "url": "/rental",    "title": "Get all rentals",    "name": "GetRentals",    "group": "Rental",    "examples": [      {        "title": "Response format:",        "content": "{\n  \"results\": [\n    \"endDate\": \"2017-02-23T05:00:00.000Z\",\n    \"itemID\": 0,\n    \"organizationID\": 0,\n    \"rentalID\": 0,\n    \"returnDate\": null,\n    \"startDate\": \"2017-02-22T05:00:00.000Z\",\n    \"tag\": \"\",\n    \"userID\": null\n  ]\n}",        "type": "json"      }    ],    "version": "0.0.0",    "filename": "controllers/rental.js",    "groupTitle": "Rental"  },  {    "type": "put",    "url": "/rental/:rentalID",    "title": "Update a rental",    "name": "UpdateRental",    "group": "Rental",    "version": "0.0.0",    "filename": "controllers/rental.js",    "groupTitle": "Rental",    "examples": [      {        "title": "Response format:",        "content": "{\n  \"endDate\": \"2017-02-23T05:00:00.000Z\",\n  \"itemID\": 0,\n  \"organizationID\": 0,\n  \"rentalID\": 0,\n  \"returnDate\": null,\n  \"startDate\": \"2017-02-22T05:00:00.000Z\",\n  \"tag\": \"\",\n  \"userID\": null\n}",        "type": "json"      }    ]  },  {    "type": "put",    "url": "/user",    "title": "Create a user",    "name": "CreateUser",    "group": "User",    "description": "<p>Not implemented.</p>",    "success": {      "fields": {        "200": [          {            "group": "200",            "optional": false,            "field": "empty",            "description": "<p>No response body</p>"          }        ]      }    },    "version": "0.0.0",    "filename": "controllers/user.js",    "groupTitle": "User"  },  {    "type": "delete",    "url": "/user/:userID",    "title": "Delete a user",    "name": "DeleteUser",    "group": "User",    "description": "<p>Not implemented.</p>",    "success": {      "fields": {        "200": [          {            "group": "200",            "optional": false,            "field": "empty",            "description": "<p>No response body</p>"          }        ]      }    },    "version": "0.0.0",    "filename": "controllers/user.js",    "groupTitle": "User"  },  {    "type": "get",    "url": "/user/:userID",    "title": "Get a user",    "name": "GetUser",    "group": "User",    "description": "<p>Not implemented.</p>",    "success": {      "fields": {        "200": [          {            "group": "200",            "optional": false,            "field": "empty",            "description": "<p>No response body</p>"          }        ]      }    },    "version": "0.0.0",    "filename": "controllers/user.js",    "groupTitle": "User"  },  {    "type": "get",    "url": "/user",    "title": "Get all users",    "name": "GetUsers",    "group": "User",    "description": "<p>Not implemented.</p>",    "success": {      "fields": {        "200": [          {            "group": "200",            "optional": false,            "field": "empty",            "description": "<p>No response body</p>"          }        ]      }    },    "version": "0.0.0",    "filename": "controllers/user.js",    "groupTitle": "User"  },  {    "type": "put",    "url": "/user/:userID",    "title": "Update a user",    "name": "UpdateUser",    "group": "User",    "version": "0.0.0",    "filename": "controllers/user.js",    "groupTitle": "User"  }]
